{"cameraMode":{"drawMode":0,"name":"Shaded","section":"Shading Mode"},"sceneLighting":true,"audioPlay":false,"sceneViewState":{"m_AlwaysRefresh":false,"showFog":true,"showSkybox":true,"showFlares":true,"showImageEffects":true,"showParticleSystems":true,"showVisualEffectGraphs":true,"m_FxEnabled":true},"in2DMode":false,"pivot":{"x":-0.26847004890441897,"y":-9.92359447479248,"z":-88.76139831542969},"rotation":{"x":-0.3858462870121002,"y":-0.050421956926584247,"z":0.015641195699572564,"w":-0.9221773147583008},"size":15.784438133239746,"orthographic":false}